dealer/__init__.py
dealer/cli.py
dealer/config.py
dealer/process/__init__.py
dealer/registry/__init__.py
dealer/supplier/__init__.py
dealer/supplier/file.py
dealer/supplier/database/__init__.py
dealer/supplier/database/athena.py
dealer/supplier/database/dynamo.py
dealer/supplier/database/mssql.py
dealer/supplier/database/redshift.py
data_dealer-0.0.4.dist-info/LICENSE
data_dealer-0.0.4.dist-info/METADATA
data_dealer-0.0.4.dist-info/WHEEL
data_dealer-0.0.4.dist-info/entry_points.txt
data_dealer-0.0.4.dist-info/top_level.txt
data_dealer-0.0.4.dist-info/RECORD
